hbc_random_number/__init__.py
hbc_random_number/hbc_random_number.py
hbc_random_number-0.2.0.dist-info/AUTHORS.rst
hbc_random_number-0.2.0.dist-info/METADATA
hbc_random_number-0.2.0.dist-info/WHEEL
hbc_random_number-0.2.0.dist-info/top_level.txt
hbc_random_number-0.2.0.dist-info/RECORD
