Metadata-Version: 2.1
Name: hbc-random-number
Version: 0.2.0
Summary: Python Boilerplate contains all the boilerplate you need to create a Python package.
Home-page: https://github.com/sarthakvijayvergiya/hbc_random_number
Author: Sarthak Vijayvergiya
Author-email: sarthak@blueprintfinance.com
License: UNKNOWN
Keywords: hbc_random_number
Platform: UNKNOWN
Classifier: Development Status :: 2 - Pre-Alpha
Classifier: Intended Audience :: Developers
Classifier: Natural Language :: English
Classifier: Programming Language :: Python :: 3.9
Requires-Python: >=3.9.13
